reader/__init__.py
reader/__main__.py
reader/config.cfg
reader/feed.py
reader/viewer.py
realpython_reader_tchia-1.3.1.dist-info/LICENSE
realpython_reader_tchia-1.3.1.dist-info/METADATA
realpython_reader_tchia-1.3.1.dist-info/WHEEL
realpython_reader_tchia-1.3.1.dist-info/entry_points.txt
realpython_reader_tchia-1.3.1.dist-info/top_level.txt
realpython_reader_tchia-1.3.1.dist-info/RECORD
