Metadata-Version: 2.1
Name: realpython-reader-tchia
Version: 1.3.1
Summary: Read the latest Real Python tutorials
Home-page: https://github.com/tchia04/realpython-reader.git
Author: Tony Chia
Author-email: tchia04@gmail.com
License: MIT
Classifier: License :: OSI Approved :: MIT License
Classifier: Programming Language :: Python
Classifier: Programming Language :: Python :: 2
Classifier: Programming Language :: Python :: 3
License-File: LICENSE
Requires-Dist: feedparser
Requires-Dist: html2text
Requires-Dist: importlib-resources
Requires-Dist: typing
